audep/__init__.py
audep/__main__.py
audep/deploy.py
audep/hdexceptions.py
audep/main.py
audep-1.2.3.dist-info/DESCRIPTION.rst
audep-1.2.3.dist-info/METADATA
audep-1.2.3.dist-info/RECORD
audep-1.2.3.dist-info/WHEEL
audep-1.2.3.dist-info/entry_points.txt
audep-1.2.3.dist-info/metadata.json
audep-1.2.3.dist-info/top_level.txt
